py_whatsapp_formatter-1.0.4.dist-info/licenses/LICENSE
whatsapp_formatter/__init__.py
whatsapp_formatter/converter.py
whatsapp_formatter/py.typed
whatsapp_formatter/rules.py
py_whatsapp_formatter-1.0.4.dist-info/METADATA
py_whatsapp_formatter-1.0.4.dist-info/WHEEL
py_whatsapp_formatter-1.0.4.dist-info/top_level.txt
py_whatsapp_formatter-1.0.4.dist-info/RECORD
