Metadata-Version: 2.4
Name: py-whatsapp-formatter
Version: 1.0.4
Summary: Convert Markdown and HTML to WhatsApp-compatible formatting
Author-email: Tejas Ambhore <tejasam2020@gmail.com>
License: MIT
Project-URL: Homepage, https://github.com/yourusername/whatsapp-formatter
Project-URL: Repository, https://github.com/yourusername/whatsapp-formatter
Project-URL: Issues, https://github.com/yourusername/whatsapp-formatter/issues
Keywords: whatsapp,markdown,html,formatter,converter
Classifier: Development Status :: 4 - Beta
Classifier: Intended Audience :: Developers
Classifier: License :: OSI Approved :: MIT License
Classifier: Operating System :: OS Independent
Classifier: Programming Language :: Python :: 3
Classifier: Programming Language :: Python :: 3.9
Classifier: Programming Language :: Python :: 3.10
Classifier: Programming Language :: Python :: 3.11
Classifier: Programming Language :: Python :: 3.12
Classifier: Programming Language :: Python :: 3.13
Classifier: Topic :: Text Processing :: Markup
Classifier: Topic :: Communications :: Chat
Classifier: Typing :: Typed
Requires-Python: >=3.9
License-File: LICENSE
Provides-Extra: dev
Requires-Dist: pytest>=7.0; extra == "dev"
Requires-Dist: pytest-cov>=4.0; extra == "dev"
Requires-Dist: mypy>=1.0; extra == "dev"
Requires-Dist: ruff>=0.1.0; extra == "dev"
Dynamic: license-file
